telegram_bottools/__init__.py
telegram_bottools/telegram_bottools.py
telegram_bottools-0.1.3.dist-info/METADATA
telegram_bottools-0.1.3.dist-info/WHEEL
telegram_bottools-0.1.3.dist-info/RECORD
