Metadata-Version: 2.1
Name: telegram-bottools
Version: 0.1.3
Summary: Telegram Bot Tools
Author: Ricardo Merces
Author-email: ricardo.merces@gmail.com
Requires-Python: >=3.11,<4.0
Classifier: Programming Language :: Python :: 3
Classifier: Programming Language :: Python :: 3.11
Requires-Dist: requests (>=2.28,<3.0)
Requires-Dist: urllib3 (>=1.26,<2.0)
